castep_outputs/__init__.py
castep_outputs/__main__.py
castep_outputs/bin_parsers/__init__.py
castep_outputs/bin_parsers/cst_esp_file_parser.py
castep_outputs/bin_parsers/fortran_bin_parser.py
castep_outputs/cli/__init__.py
castep_outputs/cli/args.py
castep_outputs/cli/castep_outputs_main.py
castep_outputs/parsers/__init__.py
castep_outputs/parsers/bands_file_parser.py
castep_outputs/parsers/castep_file_parser.py
castep_outputs/parsers/cell_param_file_parser.py
castep_outputs/parsers/efield_file_parser.py
castep_outputs/parsers/elastic_file_parser.py
castep_outputs/parsers/epme_file_parser.py
castep_outputs/parsers/err_file_parser.py
castep_outputs/parsers/hug_file_parser.py
castep_outputs/parsers/magres_file_parser.py
castep_outputs/parsers/md_geom_file_parser.py
castep_outputs/parsers/parse_fmt_files.py
castep_outputs/parsers/parse_utilities.py
castep_outputs/parsers/phonon_dos_file_parser.py
castep_outputs/parsers/phonon_file_parser.py
castep_outputs/parsers/tddft_file_parser.py
castep_outputs/parsers/ts_file_parser.py
castep_outputs/parsers/xrd_sf_file_parser.py
castep_outputs/processing/__init__.py
castep_outputs/processing/processing.py
castep_outputs/tools/__init__.py
castep_outputs/tools/get_generated_files.py
castep_outputs/utilities/__init__.py
castep_outputs/utilities/castep_res.py
castep_outputs/utilities/constants.py
castep_outputs/utilities/datatypes.py
castep_outputs/utilities/dumpers.py
castep_outputs/utilities/filewrapper.py
castep_outputs/utilities/utility.py
castep_outputs-0.2.0.dist-info/licenses/LICENSE
castep_outputs-0.2.0.dist-info/METADATA
castep_outputs-0.2.0.dist-info/WHEEL
castep_outputs-0.2.0.dist-info/entry_points.txt
castep_outputs-0.2.0.dist-info/top_level.txt
castep_outputs-0.2.0.dist-info/RECORD
