Metadata-Version: 2.4
Name: castep_outputs
Version: 0.2.0
Summary: A package for extracting information from castep outputs
Author-email: Jacob Wilkins <jacob.wilkins@stfc.ac.uk>
License: BSD-3-Clause
Project-URL: Homepage, https://github.com/oerc0122/castep_outputs
Project-URL: Documentation, https://oerc0122.github.io/castep_outputs/
Project-URL: Repository, https://github.com/oerc0122/castep_outputs.git
Project-URL: Bug Tracker, https://github.com/oerc0122/castep_outputs/issues
Keywords: castep,dft,parser
Classifier: Development Status :: 4 - Beta
Classifier: Intended Audience :: Science/Research
Classifier: Topic :: File Formats :: JSON
Classifier: Topic :: Scientific/Engineering :: Physics
Classifier: License :: OSI Approved :: BSD License
Classifier: Programming Language :: Python :: 3
Classifier: Programming Language :: Python :: 3.9
Classifier: Programming Language :: Python :: 3.10
Classifier: Programming Language :: Python :: 3.11
Classifier: Programming Language :: Python :: 3.12
Requires-Python: >=3.9
License-File: LICENSE
Provides-Extra: ruamel
Requires-Dist: ruamel.yaml>=0.17.22; extra == "ruamel"
Provides-Extra: yaml
Requires-Dist: pyYAML>=3.13; extra == "yaml"
Provides-Extra: docs
Requires-Dist: jupyter-book>=0.13.1; extra == "docs"
Requires-Dist: sphinx-book-theme>=0.3.3; extra == "docs"
Requires-Dist: sphinx-argparse>=0.4.0; extra == "docs"
Requires-Dist: sphinx-autodoc-typehints; extra == "docs"
Provides-Extra: lint
Requires-Dist: ruff==0.8.0; extra == "lint"
Provides-Extra: test
Requires-Dist: pytest==8.3.4; extra == "test"
Requires-Dist: pytest-cov==5.0.0; extra == "test"
Dynamic: license-file
